bridgic/traces/opik/__init__.py
bridgic/traces/opik/_opik_trace_callback.py
bridgic_traces_opik-0.1.0.dist-info/METADATA
bridgic_traces_opik-0.1.0.dist-info/WHEEL
bridgic_traces_opik-0.1.0.dist-info/licenses/LICENSE
bridgic_traces_opik-0.1.0.dist-info/RECORD
