Metadata-Version: 2.4
Name: bridgic-traces-opik
Version: 0.1.0
Summary: Opik observability integration for Bridgic.
Author-email: Tielei Zhang <zhangtl04@gmail.com>
License: MIT
License-File: LICENSE
Classifier: Programming Language :: Python :: 3
Requires-Python: >=3.9
Requires-Dist: bridgic-core>=0.1.2
Requires-Dist: opik>=1.8.97
Requires-Dist: urllib3<2.0
